gallery/__init__.py
gallery/admin.py
gallery/apps.py
gallery/static/css/gallery/bethany_ds.css
gallery/static/css/gallery/medicio_ds.css
gallery/static/css/gallery/medilab_ds.css
gallery/templates/gallery/_common.html
gallery/templates/gallery/bethany_ds.html
gallery/templates/gallery/medicio_ds.html
gallery/templates/gallery/medilab_ds.html
gallery/templatetags/__init__.py
gallery/templatetags/gallery_tags.py
django_gallery_ds-1.1.0.dist-info/LICENSE
django_gallery_ds-1.1.0.dist-info/METADATA
django_gallery_ds-1.1.0.dist-info/WHEEL
django_gallery_ds-1.1.0.dist-info/top_level.txt
django_gallery_ds-1.1.0.dist-info/RECORD
